WorldTimeAPI/__init__.py
WorldTimeAPI/schemas.py
WorldTimeAPI/service.py
world_time_api-2020.5.31.dist-info/LICENSE
world_time_api-2020.5.31.dist-info/METADATA
world_time_api-2020.5.31.dist-info/WHEEL
world_time_api-2020.5.31.dist-info/top_level.txt
world_time_api-2020.5.31.dist-info/RECORD
