Metadata-Version: 2.1
Name: world-time-api
Version: 2020.5.31
Summary: A wrapper for the World Time API.
Home-page: https://github.com/Dulatr/WorldTimeAPI
Author: Tyler Dula
Author-email: echo.dulatr@gmail.com
License: UNKNOWN
Platform: UNKNOWN
Classifier: Programming Language :: Python :: 3
Classifier: License :: OSI Approved :: MIT License
Classifier: Operating System :: OS Independent
Requires-Python: >=3.6
